exactcli/__init__.py
exactcli/__main__.py
exactcli-0.0.1.dist-info/METADATA
exactcli-0.0.1.dist-info/WHEEL
exactcli-0.0.1.dist-info/entry_points.txt
exactcli-0.0.1.dist-info/licenses/LICENSE
exactcli-0.0.1.dist-info/RECORD
