Metadata-Version: 2.1
Name: exactcli
Version: 0.0.1
Summary: CLI utility and python client package for Exact headless CMS
Project-URL: Homepage, https://github.com/yaroslaff/exactcli
Project-URL: Issues, https://github.com/yaroslaff/exactcli/issues
Author-email: Yaroslav Polyakov <yaroslaff@gmail.com>
License-File: LICENSE
Classifier: License :: OSI Approved :: MIT License
Classifier: Operating System :: OS Independent
Classifier: Programming Language :: Python :: 3
Requires-Python: >=3.9
Requires-Dist: python-dotenv
Requires-Dist: requests
